{
    "tip": "hikaye",
    "sayfalar": [
        "In the Class\n\nI go to the classroom. I Open the door. Then, I Close the door.\n\nI See my teacher. He says, \"Please Look at the board.\"\n\nI Hear my friends, but I Listen to the teacher carefully.\n\nWe Speak English in the lesson. I Say, \"I have a question.\"\n\nI Ask the question. The teacher Answers very well."
    ],
    "sozluk": {
        "lesson": "ders",
        "friends": "Arkadaşlar",
        "english": "İngilizce",
        "but": "Ancak",
        "he": "O",
        "carefully": "dikkatlice",
        "well": "Peki",
        "we": "Biz",
        "then": "Daha sonra",
        "the": "the",
        "at": "en",
        "in": "içinde",
        "says": "diyor",
        "my": "Benim",
        "question": "soru",
        "very": "çok",
        "board": "pano",
        "class": "sınıf",
        "have": "sahip olmak",
        "answers": "cevaplar",
        "please": "Lütfen",
        "to": "ile",
        "classroom": "sınıf"
    }
}